{
  "python.linting.enabled": true,
  "python.linting.flake8Enabled": true,
  "python.linting.flake8Path": "/home/ben/.programs/anaconda3/envs/neovim3/bin/flake8",
  "python.linting.flake8Args": ["--verbose", "--max-line-length", "110"],
  "python.linting.pylintArgs": ["--ignored-modules", "netCDF4", "--line-length", "110"],

  "python.formatting.provider": "black",
  "python.formatting.blackPath": "/home/ben/.programs/anaconda3/envs/neovim3/bin/black",
  "python.formatting.blackArgs": ["--line-length", "110"],

  "python.condaPath": "/home/ben/.programs/anaconda3/bin/conda",
  "latex.build.executable": "/usr/bin/pdflatex",
  "latex.build.onSave": true,
  "latex.build.outputDirectory": ".",
  "latex.lint.onSave": true,
  "latex.forwardSearch.executable": "evince",

  "html.filetypes": [ "html", "handlebars", "inc"],
  "html.format.enable": true,

  "r.lsp.path": "~/R/x86_64-pc-linux-gnu-library/3.6/languageserver/R/languageserver",

  "languageserver": {
      "bash": {
          "command": "bash-language-server",
          "args": ["start"],
          "filetypes": ["sh"]
      }
  },

  "session.saveOnVimLeave": true,
  "list.source.tags.command": "git ctags"
}
